.DS_Store
omnisense/.DS_Store
omnisense/__init__.py
omnisense/bin/__init__.py
omnisense/bin/cli_base.py
omnisense/bin/omnisense.py
omnisense/models/__init__.py
omnisense/models/k2_utils.py
omnisense/models/model.py
omnisense/models/sensevoice.py
OmniSenseVoice-0.2.0.dist-info/LICENSE
OmniSenseVoice-0.2.0.dist-info/METADATA
OmniSenseVoice-0.2.0.dist-info/WHEEL
OmniSenseVoice-0.2.0.dist-info/entry_points.txt
OmniSenseVoice-0.2.0.dist-info/top_level.txt
OmniSenseVoice-0.2.0.dist-info/RECORD
