Metadata-Version: 2.1
Name: OmniSenseVoice
Version: 0.2.0
Summary: OmniSenseVoice
Home-page: https://github.com/lifeiteng/OmniSenseVoice
Download-URL: https://github.com/lifeiteng/OmniSenseVoice/releases
Author: lifeiteng0422@gmail.com
Classifier: Development Status :: 5 - Production/Stable
Classifier: Programming Language :: Python :: 3.8
Classifier: Programming Language :: Python :: 3.9
Classifier: Programming Language :: Python :: 3.10
Classifier: Programming Language :: Python :: 3.11
Classifier: Programming Language :: Python :: 3.12
Classifier: Intended Audience :: Science/Research
Classifier: Operating System :: POSIX :: Linux
Classifier: Operating System :: MacOS :: MacOS X
Classifier: Operating System :: Microsoft :: Windows
Classifier: License :: OSI Approved :: Apache Software License
Classifier: Topic :: Multimedia :: Sound/Audio :: Speech
Classifier: Topic :: Scientific/Engineering :: Artificial Intelligence
Classifier: Topic :: Software Development :: Libraries :: Python Modules
Classifier: Typing :: Typed
Requires-Python: >=3.8
License-File: LICENSE
Requires-Dist: funasr-onnx==0.4.1
Requires-Dist: modelscope==1.18.0
Requires-Dist: funasr==1.1.6
Requires-Dist: lhotse>=1.24.2
Requires-Dist: kaldialign
Requires-Dist: torch
Requires-Dist: torchaudio
